ltctplugin/upk2esphome/__init__.py
ltctplugin/upk2esphome/cli.py
ltctplugin/upk2esphome/common.py
ltctplugin/upk2esphome/gui.py
ltctplugin/upk2esphome/upk2esphome.wxui
ltctplugin/upk2esphome/upk2esphome.xrc
ltctplugin/upk2esphome/work.py
ltctplugin/upk2esphome/work_schema.py
upk2esphome/__init__.py
upk2esphome/config.py
upk2esphome/const.py
upk2esphome/datapoints/__init__.py
upk2esphome/datapoints/category/base.py
upk2esphome/datapoints/category/dlq.json
upk2esphome/datapoints/category/wsdcg.json
upk2esphome/datapoints/converter.py
upk2esphome/datapoints/mapping/common.json
upk2esphome/datapoints/mapping/electricity.json
upk2esphome/datapoints/mapping/environmental.json
upk2esphome/datapoints/model.py
upk2esphome/datapoints/utils.py
upk2esphome/generator.py
upk2esphome/oldfmt.py
upk2esphome/opts.py
upk2esphome/parts/__init__.py
upk2esphome/parts/bulb.py
upk2esphome/parts/key.py
upk2esphome/parts/module.py
upk2esphome/parts/monitor.py
upk2esphome/parts/netled.py
upk2esphome/parts/remote.py
upk2esphome/parts/static.py
upk2esphome/parts/switch.py
upk2esphome/parts/tuyamcu.py
upk2esphome/result.py
upk2esphome/test.py
upk2esphome/tests/breaker_hbridge.txt
upk2esphome/tests/bulb_pwm_ct.txt
upk2esphome/tests/bulb_pwm_cw.txt
upk2esphome/tests/bulb_pwm_rgbct.txt
upk2esphome/tests/bulb_pwm_rgbcw.txt
upk2esphome/tests/bulb_rgbc_2135_2.txt
upk2esphome/tests/bulb_rgbcw_2135.txt
upk2esphome/tests/bulb_rgbcw_2135_ampere.txt
upk2esphome/tests/bulb_rgbcw_2235.txt
upk2esphome/tests/bulb_rgbcw_5758d.txt
upk2esphome/tests/empty.txt
upk2esphome/tests/expected_output/breaker_hbridge.yaml
upk2esphome/tests/expected_output/bulb_pwm_ct.yaml
upk2esphome/tests/expected_output/bulb_pwm_cw.yaml
upk2esphome/tests/expected_output/bulb_pwm_rgbct.yaml
upk2esphome/tests/expected_output/bulb_pwm_rgbcw.yaml
upk2esphome/tests/expected_output/bulb_rgbc_2135_2.yaml
upk2esphome/tests/expected_output/bulb_rgbcw_2135.yaml
upk2esphome/tests/expected_output/bulb_rgbcw_2135_ampere.yaml
upk2esphome-1.16.1.dist-info/METADATA
upk2esphome-1.16.1.dist-info/WHEEL
upk2esphome-1.16.1.dist-info/licenses/LICENSE
upk2esphome-1.16.1.dist-info/RECORD
