Metadata-Version: 2.4
Name: upk2esphome
Version: 1.16.1
Summary: Convert Tuya device configuration to ESPHome YAML (ltchiptool plugin)
License: MIT
License-File: LICENSE
Author: Kuba Szczodrzyński
Author-email: kuba@szczodrzynski.pl
Requires-Python: >=3.10,<4.0
Classifier: License :: OSI Approved :: MIT License
Classifier: Programming Language :: Python :: 3
Classifier: Programming Language :: Python :: 3.10
Classifier: Programming Language :: Python :: 3.11
Classifier: Programming Language :: Python :: 3.12
Classifier: Programming Language :: Python :: 3.13
Classifier: Programming Language :: Python :: 3.14
Requires-Dist: PyYAML (>=6.0,<7.0)
Requires-Dist: inquirer (>=3.1.3,<4.0.0)
Requires-Dist: requests (>=2.31.0,<3.0.0)
